kafkahelpers/__init__.py
kafkahelpers/test_reconnecting.py
kafkahelpers-0.3.3.dist-info/LICENSE
kafkahelpers-0.3.3.dist-info/WHEEL
kafkahelpers-0.3.3.dist-info/METADATA
kafkahelpers-0.3.3.dist-info/RECORD
