Metadata-Version: 2.1
Name: kafkahelpers
Version: 0.3.3
Summary: 
Home-page: UNKNOWN
License: UNKNOWN
Author: Jesse Jaggars
Author-email: jhjaggars@gmail.com
Requires-Python: >=3.6,<4.0
Classifier: Programming Language :: Python :: 3
Classifier: Programming Language :: Python :: 3.6
Classifier: Programming Language :: Python :: 3.7
Requires-Dist: aiokafka (>=0.5.0,<0.6.0)
Requires-Dist: attrs (>=18.2,<19.0)
Requires-Dist: kafka-python (>=1.4,<2.0)
